airflow/providers/databricks/__init__.py
airflow/providers/databricks/exceptions.py
airflow/providers/databricks/get_provider_info.py
airflow/providers/databricks/version_compat.py
airflow/providers/databricks/hooks/__init__.py
airflow/providers/databricks/hooks/databricks.py
airflow/providers/databricks/hooks/databricks_base.py
airflow/providers/databricks/hooks/databricks_sql.py
airflow/providers/databricks/operators/__init__.py
airflow/providers/databricks/operators/databricks.py
airflow/providers/databricks/operators/databricks_repos.py
airflow/providers/databricks/operators/databricks_sql.py
airflow/providers/databricks/operators/databricks_workflow.py
airflow/providers/databricks/plugins/__init__.py
airflow/providers/databricks/plugins/databricks_workflow.py
airflow/providers/databricks/sensors/__init__.py
airflow/providers/databricks/sensors/databricks.py
airflow/providers/databricks/sensors/databricks_partition.py
airflow/providers/databricks/sensors/databricks_sql.py
airflow/providers/databricks/triggers/__init__.py
airflow/providers/databricks/triggers/databricks.py
airflow/providers/databricks/utils/__init__.py
airflow/providers/databricks/utils/databricks.py
airflow/providers/databricks/utils/mixins.py
airflow/providers/databricks/utils/openlineage.py
apache_airflow_providers_databricks-7.8.3.dist-info/entry_points.txt
apache_airflow_providers_databricks-7.8.3.dist-info/licenses/LICENSE
apache_airflow_providers_databricks-7.8.3.dist-info/licenses/NOTICE
apache_airflow_providers_databricks-7.8.3.dist-info/WHEEL
apache_airflow_providers_databricks-7.8.3.dist-info/METADATA
apache_airflow_providers_databricks-7.8.3.dist-info/RECORD
