Metadata-Version: 2.4
Name: apache-airflow-providers-databricks
Version: 7.8.3
Summary: Provider package apache-airflow-providers-databricks for Apache Airflow
Keywords: airflow-provider,databricks,airflow,integration
Author-email: Apache Software Foundation <dev@airflow.apache.org>
Maintainer-email: Apache Software Foundation <dev@airflow.apache.org>
Requires-Python: >=3.10
License-Expression: Apache-2.0
Classifier: Development Status :: 5 - Production/Stable
Classifier: Environment :: Console
Classifier: Environment :: Web Environment
Classifier: Intended Audience :: Developers
Classifier: Intended Audience :: System Administrators
Classifier: Framework :: Apache Airflow
Classifier: Framework :: Apache Airflow :: Provider
Classifier: Programming Language :: Python :: 3.10
Classifier: Programming Language :: Python :: 3.11
Classifier: Programming Language :: Python :: 3.12
Classifier: Programming Language :: Python :: 3.13
Classifier: Topic :: System :: Monitoring
License-File: LICENSE
License-File: NOTICE
Requires-Dist: apache-airflow>=2.11.0
Requires-Dist: apache-airflow-providers-common-compat>=1.12.0
Requires-Dist: apache-airflow-providers-common-sql>=1.27.0
Requires-Dist: requests>=2.32.0,<3
Requires-Dist: databricks-sql-connector>=4.0.0
Requires-Dist: aiohttp>=3.9.2, <4
Requires-Dist: mergedeep>=1.3.4
Requires-Dist: pandas>=2.1.2; python_version <"3.13"
Requires-Dist: pandas>=2.2.3; python_version >="3.13"
Requires-Dist: pyarrow>=16.1.0; python_version < '3.13'
Requires-Dist: pyarrow>=18.0.0; python_version >= '3.13'
Requires-Dist: azure-identity>=1.3.1 ; extra == "azure-identity"
Requires-Dist: apache-airflow-providers-fab>=2.2.0 ; extra == "fab" and ( python_version < '3.13')
Requires-Dist: apache-airflow-providers-openlineage>=2.3.0 ; extra == "openlineage"
Requires-Dist: databricks-sdk==0.10.0 ; extra == "sdk"
Requires-Dist: databricks-sqlalchemy>=1.0.2 ; extra == "sqlalchemy"
Requires-Dist: apache-airflow-providers-standard ; extra == "standard"
Project-URL: Bug Tracker, https://github.com/apache/airflow/issues
Project-URL: Changelog, https://airflow.apache.org/docs/apache-airflow-providers-databricks/7.8.3/changelog.html
Project-URL: Documentation, https://airflow.apache.org/docs/apache-airflow-providers-databricks/7.8.3
Project-URL: Mastodon, https://fosstodon.org/@airflow
Project-URL: Slack Chat, https://s.apache.org/airflow-slack
Project-URL: Source Code, https://github.com/apache/airflow
Project-URL: YouTube, https://www.youtube.com/channel/UCSXwxpWZQ7XZ1WL3wqevChA/
Provides-Extra: azure-identity
Provides-Extra: fab
Provides-Extra: openlineage
Provides-Extra: sdk
Provides-Extra: sqlalchemy
Provides-Extra: standard
